{"DSPlayer":[{"Breakpoints":[{"Breakpoint":"MIN5","Gas":0,"Income":2023,"Army":4261,"Kills":4735,"Upgrades":425,"Tier":0,"Mid":0,"dsUnitsString":"Stalker,9|Sentry,2|Adept,7","dbUnitsString":"Stalker,166,172|Stalker,167,170|Stalker,169,168|Stalker,171,165|Sentry,171,168|Stalker,173,164|Stalker,175,162|Stalker,177,160|Stalker,179,158|Stalker,180,157|Adept,168,169|Adept,174,163|Adept,178,159|Sentry,177,162|Adept,170,167|Adept,176,161|Adept,165,171|Adept,179,157","dbUpgradesString":"BlinkTech|ProtossGroundWeaponsLevel1|AdeptPiercingAttack"},{"Breakpoint":"MIN10","Gas":0,"Income":4519,"Army":18095,"Kills":20295,"Upgrades":1225,"Tier":0,"Mid":0,"dsUnitsString":"Stalker,20|Sentry,2|Adept,7|Disruptor,2|Observer,1","dbUnitsString":"Stalker,166,172|Stalker,167,170|Stalker,169,168|Stalker,171,165|Sentry,171,168|Stalker,173,164|Stalker,175,162|Stalker,177,160|Stalker,179,158|Stalker,180,157|Adept,168,169|Adept,174,163|Adept,178,159|Sentry,177,162|Adept,170,167|Adept,176,161|Adept,165,171|Adept,179,157|Stalker,166,168|Stalker,164,170|Stalker,168,166|Stalker,169,164|Disruptor,178,156|Stalker,171,162|Stalker,173,160|Stalker,175,160|Stalker,177,158|Observer,172,162|Disruptor,163,168|Stalker,166,165|Stalker,167,164|Stalker,169,162","dbUpgradesString":"ProtossGroundArmorsLevel1|Tier2|NeosteelFrame|ProtossShieldsLevel1|ProtossGroundWeaponsLevel2|ProtossShieldsLevel2|ProtossGroundArmorsLevel2"},{"Breakpoint":"ALL","Gas":1,"Income":5512,"Army":25950,"Kills":31950,"Upgrades":1300,"Tier":0,"Mid":0,"dsUnitsString":"Stalker,22|Sentry,2|Adept,7|Disruptor,3|Observer,1","dbUnitsString":"Stalker,166,172|Stalker,167,170|Stalker,169,168|Stalker,171,165|Sentry,171,168|Stalker,173,164|Stalker,175,162|Stalker,177,160|Stalker,179,158|Stalker,180,157|Adept,168,169|Adept,174,163|Adept,178,159|Sentry,177,162|Adept,170,167|Adept,176,161|Adept,165,171|Adept,179,157|Stalker,166,168|Stalker,164,170|Stalker,168,166|Stalker,169,164|Disruptor,178,156|Stalker,171,162|Stalker,173,160|Stalker,175,160|Stalker,177,158|Observer,172,162|Disruptor,163,168|Stalker,166,165|Stalker,167,164|Stalker,169,162|Disruptor,171,161|Stalker,175,158|Stalker,172,159","dbUpgradesString":"VoidRaySpeedUpgrade"}],"POS":1,"REALPOS":1,"NAME":"gupihuj","RACE":"Protoss","OPPRACE":"Terran","WIN":true,"TEAM":0,"KILLSUM":31950,"INCOME":5512,"PDURATION":721,"ARMY":25950,"GAS":1},{"Breakpoints":[{"Breakpoint":"MIN5","Gas":0,"Income":2023,"Army":4950,"Kills":4125,"Upgrades":250,"Tier":0,"Mid":0,"dsUnitsString":"Marine,37","dbUnitsString":"Marine,154,163|Marine,155,162|Marine,156,161|Marine,157,160|Marine,158,159|Marine,159,158|Marine,160,157|Marine,161,156|Marine,162,155|Marine,163,154|Marine,164,153|Marine,165,152|Marine,166,151|Marine,167,150|Marine,168,149|Marine,169,148|Marine,170,147|Marine,171,146|Marine,155,163|Marine,156,162|Marine,157,161|Marine,158,160|Marine,159,159|Marine,160,158|Marine,161,157|Marine,162,156|Marine,163,155|Marine,164,154|Marine,165,154|Marine,165,153|Marine,166,152|Marine,167,151|Marine,168,150|Marine,169,149|Marine,170,148|Marine,171,147|Marine,172,147","dbUpgradesString":"ShieldWall|Stimpack|TerranInfantryWeaponsLevel1"},{"Breakpoint":"MIN10","Gas":1,"Income":4633,"Army":20267,"Kills":18235,"Upgrades":825,"Tier":0,"Mid":0,"dsUnitsString":"Marine,54|Liberator,4|Raven,1","dbUnitsString":"Marine,154,163|Marine,155,162|Marine,156,161|Marine,157,160|Marine,158,159|Marine,159,158|Marine,160,157|Marine,161,156|Marine,162,155|Marine,163,154|Marine,164,153|Marine,165,152|Marine,166,151|Marine,167,150|Marine,168,149|Marine,169,148|Marine,170,147|Marine,171,146|Marine,155,163|Marine,156,162|Marine,157,161|Marine,158,160|Marine,159,159|Marine,160,158|Marine,161,157|Marine,162,156|Marine,163,155|Marine,164,154|Marine,165,154|Marine,165,153|Marine,166,152|Marine,167,151|Marine,168,150|Marine,169,149|Marine,170,148|Marine,171,147|Marine,172,147|Marine,171,148|Marine,171,149|Marine,170,149|Marine,169,150|Marine,168,151|Marine,167,152|Marine,166,153|Marine,164,155|Marine,163,156|Marine,162,157|Marine,161,158|Marine,160,159|Marine,159,160|Marine,158,161|Marine,157,162|Marine,156,163|Marine,155,164|Liberator,157,164|Liberator,172,150|Raven,166,160|Liberator,159,163|Liberator,170,153","dbUpgradesString":"TerranInfantryArmorsLevel1|Tier2|NeosteelFrame|TerranInfantryWeaponsLevel2|TerranInfantryArmorsLevel2|TerranShipWeaponsLevel1|TerranShipWeaponsLevel2"},{"Breakpoint":"ALL","Gas":1,"Income":5637,"Army":29462,"Kills":21480,"Upgrades":825,"Tier":0,"Mid":0,"dsUnitsString":"Marine,54|Liberator,8|Raven,1|WidowMine,1","dbUnitsString":"Marine,154,163|Marine,155,162|Marine,156,161|Marine,157,160|Marine,158,159|Marine,159,158|Marine,160,157|Marine,161,156|Marine,162,155|Marine,163,154|Marine,164,153|Marine,165,152|Marine,166,151|Marine,167,150|Marine,168,149|Marine,169,148|Marine,170,147|Marine,171,146|Marine,155,163|Marine,156,162|Marine,157,161|Marine,158,160|Marine,159,159|Marine,160,158|Marine,161,157|Marine,162,156|Marine,163,155|Marine,164,154|Marine,165,154|Marine,165,153|Marine,166,152|Marine,167,151|Marine,168,150|Marine,169,149|Marine,170,148|Marine,171,147|Marine,172,147|Marine,171,148|Marine,171,149|Marine,170,149|Marine,169,150|Marine,168,151|Marine,167,152|Marine,166,153|Marine,164,155|Marine,163,156|Marine,162,157|Marine,161,158|Marine,160,159|Marine,159,160|Marine,158,161|Marine,157,162|Marine,156,163|Marine,155,164|Liberator,157,164|Liberator,172,150|Raven,166,160|Liberator,159,163|Liberator,170,153|Liberator,161,162|Liberator,169,156|Liberator,163,162|Liberator,168,159|WidowMine,165,159","dbUpgradesString":""}],"POS":2,"REALPOS":2,"NAME":"Tellos","RACE":"Terran","OPPRACE":"Zerg","WIN":true,"TEAM":0,"KILLSUM":21480,"INCOME":5637,"PDURATION":721,"ARMY":29462,"GAS":1},{"Breakpoints":[{"Breakpoint":"MIN5","Gas":0,"Income":2023,"Army":5062,"Kills":3150,"Upgrades":275,"Tier":0,"Mid":0,"dsUnitsString":"Roach,16|Queen,2","dbUnitsString":"Roach,170,167|Roach,165,172|Roach,175,162|Roach,164,173|Roach,169,168|Roach,174,163|Roach,173,164|Roach,172,165|Roach,171,166|Roach,176,161|Roach,167,170|Roach,166,171|Roach,178,159|Queen,168,169|Queen,177,160|Roach,179,158|Roach,180,157|Roach,181,156","dbUpgradesString":"ZergMissileWeaponsLevel1|ZergGroundArmorsLevel1"},{"Breakpoint":"MIN10","Gas":1,"Income":4613,"Army":20917,"Kills":14150,"Upgrades":625,"Tier":0,"Mid":0,"dsUnitsString":"Roach,16|Queen,6|Hydralisk,14|Lurker,1","dbUnitsString":"Roach,170,167|Roach,166,170|Roach,175,162|Roach,164,173|Roach,169,168|Roach,169,167|Roach,173,164|Roach,172,165|Roach,175,161|Roach,176,161|Roach,167,170|Roach,166,171|Roach,178,159|Queen,168,169|Queen,177,160|Roach,179,158|Roach,178,158|Roach,181,156|Hydralisk,170,169|Hydralisk,171,168|Hydralisk,177,162|Hydralisk,176,163|Queen,174,163|Hydralisk,173,166|Queen,171,166|Hydralisk,174,165|Hydralisk,168,171|Hydralisk,179,160|Hydralisk,167,172|Hydralisk,180,159|Hydralisk,179,159|Hydralisk,167,171|Hydralisk,182,157|Hydralisk,165,174|Queen,166,172|Queen,180,158|Lurker,168,167","dbUpgradesString":"Tier2|NeosteelFrame|ZergMissileWeaponsLevel2|ZergGroundArmorsLevel2|EvolveGroovedSpines"},{"Breakpoint":"ALL","Gas":1,"Income":5614,"Army":30502,"Kills":24045,"Upgrades":725,"Tier":0,"Mid":0,"dsUnitsString":"Roach,16|Queen,6|Hydralisk,14|Lurker,4|Overseer,1","dbUnitsString":"Roach,170,167|Roach,166,170|Roach,175,162|Roach,164,173|Roach,169,168|Roach,169,167|Roach,173,164|Roach,172,165|Roach,175,161|Roach,176,161|Roach,167,170|Roach,166,171|Roach,178,159|Queen,168,169|Queen,177,160|Roach,179,158|Roach,178,158|Roach,181,156|Hydralisk,170,169|Hydralisk,171,168|Hydralisk,177,162|Hydralisk,176,163|Queen,174,163|Hydralisk,173,166|Queen,171,166|Hydralisk,174,165|Hydralisk,168,171|Hydralisk,179,160|Hydralisk,167,172|Hydralisk,180,159|Hydralisk,179,159|Hydralisk,167,171|Hydralisk,182,157|Hydralisk,165,174|Queen,166,172|Queen,180,158|Lurker,168,167|Lurker,175,160|Overseer,172,164|Lurker,170,165|Lurker,173,162","dbUpgradesString":"LurkerRange"}],"POS":3,"REALPOS":3,"NAME":"Baltar","RACE":"Zerg","OPPRACE":"Protoss","WIN":true,"TEAM":0,"KILLSUM":24045,"INCOME":5614,"PDURATION":721,"ARMY":30502,"GAS":1},{"Breakpoints":[{"Breakpoint":"MIN5","Gas":0,"Income":1963,"Army":3820,"Kills":4340,"Upgrades":375,"Tier":0,"Mid":0,"dsUnitsString":"Marine,10|Marauder,16","dbUnitsString":"Marine,88,81|Marine,87,82|Marauder,88,84|Marauder,91,86|Marauder,92,80|Marauder,94,78|Marauder,86,86|Marauder,96,76|Marauder,84,88|Marauder,98,74|Marauder,82,90|Marauder,85,87|Marauder,97,75|Marauder,95,77|Marauder,93,79|Marauder,94,83|Marauder,89,83|Marauder,87,85|Marine,89,80|Marine,90,79|Marine,91,78|Marine,92,77|Marine,86,83|Marine,85,84|Marine,84,85|Marine,83,86","dbUpgradesString":"ShieldWall|PunisherGrenades|Stimpack|TerranInfantryWeaponsLevel1|TerranInfantryArmorsLevel1"},{"Breakpoint":"MIN10","Gas":1,"Income":4264,"Army":16234,"Kills":18680,"Upgrades":500,"Tier":0,"Mid":0,"dsUnitsString":"Marine,27|Marauder,22|Reaper,2|HellionTank,5","dbUnitsString":"Marine,88,81|Marine,87,82|Marauder,88,84|Marauder,83,91|Marauder,92,80|Marauder,94,78|Marauder,86,86|Marauder,96,76|Marauder,84,88|Marauder,98,74|Marauder,82,90|Marauder,85,87|Marauder,97,75|Marauder,95,77|Marauder,93,79|Marauder,83,89|Marauder,89,83|Marauder,87,85|Marine,89,80|Marine,90,79|Marine,91,78|Marine,92,77|Marine,86,83|Marine,85,84|Marine,84,85|Marine,83,86|Reaper,88,83|Reaper,93,78|Marine,93,76|Marine,94,75|Marine,95,74|Marine,82,87|Marine,96,73|Marine,97,72|Marine,81,88|Marauder,91,81|Marauder,90,82|Marine,80,89|Marine,97,73|Marine,96,74|Marine,95,75|Marine,94,76|Marine,93,77|Marine,92,78|Marine,91,79|Marauder,100,75|Marauder,98,77|Marauder,96,79|Marauder,85,89|HellionTank,85,91|HellionTank,88,87|HellionTank,92,83|HellionTank,97,78|HellionTank,94,80|Marine,90,80|Marine,89,81","dbUpgradesString":"Tier2|NeosteelFrame|TerranInfantryWeaponsLevel2"},{"Breakpoint":"ALL","Gas":2,"Income":5293,"Army":22588,"Kills":24665,"Upgrades":575,"Tier":0,"Mid":0,"dsUnitsString":"Marine,27|Marauder,22|Reaper,2|HellionTank,5|Liberator,1","dbUnitsString":"Marine,88,81|Marine,87,82|Marauder,88,84|Marauder,83,91|Marauder,92,80|Marauder,94,78|Marauder,86,86|Marauder,96,76|Marauder,84,88|Marauder,98,74|Marauder,82,90|Marauder,85,87|Marauder,97,75|Marauder,95,77|Marauder,93,79|Marauder,83,89|Marauder,89,83|Marauder,87,85|Marine,89,80|Marine,90,79|Marine,91,78|Marine,92,77|Marine,86,83|Marine,85,84|Marine,84,85|Marine,83,86|Reaper,88,83|Reaper,93,78|Marine,93,76|Marine,94,75|Marine,95,74|Marine,82,87|Marine,96,73|Marine,97,72|Marine,81,88|Marauder,91,81|Marauder,90,82|Marine,80,89|Marine,97,73|Marine,96,74|Marine,95,75|Marine,94,76|Marine,93,77|Marine,92,78|Marine,91,79|Marauder,100,75|Marauder,98,77|Marauder,96,79|Marauder,85,89|HellionTank,85,91|HellionTank,88,87|HellionTank,92,83|HellionTank,97,78|HellionTank,94,80|Marine,90,80|Marine,89,81|Liberator,85,86","dbUpgradesString":"HighCapacityBarrels"}],"POS":4,"REALPOS":4,"NAME":"Futocsiga","RACE":"Terran","OPPRACE":"Protoss","WIN":false,"TEAM":1,"KILLSUM":24665,"INCOME":5293,"PDURATION":724,"ARMY":22588,"GAS":2},{"Breakpoints":[{"Breakpoint":"MIN5","Gas":0,"Income":1963,"Army":4690,"Kills":2720,"Upgrades":250,"Tier":0,"Mid":0,"dsUnitsString":"Zergling,25|Baneling,13|Roach,10","dbUnitsString":"Zergling,90,87|Zergling,91,86|Zergling,92,85|Zergling,93,84|Zergling,94,83|Zergling,95,82|Zergling,96,81|Zergling,89,88|Zergling,88,89|Zergling,87,90|Zergling,86,91|Zergling,85,92|Zergling,84,93|Zergling,97,80|Zergling,98,79|Zergling,99,78|Zergling,100,77|Zergling,101,76|Baneling,80,75|Baneling,79,76|Baneling,82,73|Baneling,81,74|Zergling,94,82|Baneling,83,72|Zergling,95,81|Roach,88,83|Roach,89,82|Roach,90,81|Roach,91,80|Roach,92,79|Roach,87,84|Roach,93,78|Roach,86,85|Roach,85,86|Roach,94,77|Zergling,96,80|Zergling,97,79|Zergling,98,78|Zergling,99,77|Zergling,100,76|Baneling,84,80|Baneling,85,79|Baneling,78,77|Baneling,77,78|Baneling,76,79|Baneling,86,78|Baneling,87,77|Baneling,88,76","dbUpgradesString":"zerglingmovementspeed|CentrificalHooks"},{"Breakpoint":"MIN10","Gas":2,"Income":4281,"Army":17579,"Kills":10540,"Upgrades":450,"Tier":0,"Mid":0,"dsUnitsString":"Zergling,55|Baneling,12|Roach,13|Lurker,3","dbUnitsString":"Zergling,90,87|Zergling,91,86|Zergling,92,85|Zergling,93,84|Zergling,94,83|Zergling,95,82|Zergling,96,81|Zergling,89,88|Zergling,88,89|Zergling,87,90|Zergling,86,91|Zergling,85,92|Zergling,84,93|Zergling,97,80|Zergling,98,79|Zergling,99,78|Zergling,100,77|Zergling,101,76|Baneling,78,87|Zergling,94,82|Zergling,95,81|Roach,88,83|Roach,89,82|Roach,90,81|Roach,91,80|Roach,92,79|Roach,87,84|Roach,93,78|Roach,86,85|Roach,85,86|Roach,94,77|Zergling,96,80|Zergling,97,79|Zergling,98,78|Zergling,99,77|Zergling,100,76|Baneling,82,91|Baneling,83,92|Baneling,95,70|Baneling,96,71|Baneling,97,72|Baneling,98,73|Baneling,81,90|Baneling,80,89|Baneling,79,88|Baneling,99,74|Baneling,100,75|Roach,84,87|Roach,83,88|Roach,95,76|Lurker,90,76|Lurker,88,78|Lurker,87,79|Zergling,93,82|Zergling,93,83|Zergling,92,84|Zergling,91,85|Zergling,90,86|Zergling,89,87|Zergling,88,88|Zergling,87,89|Zergling,86,90|Zergling,85,91|Zergling,84,92|Zergling,84,91|Zergling,85,90|Zergling,86,89|Zergling,87,88|Zergling,88,87|Zergling,89,86|Zergling,90,85|Zergling,91,84|Zergling,92,83|Zergling,94,81|Zergling,95,80|Zergling,96,79|Zergling,97,78|Zergling,98,77|Zergling,99,76|Zergling,99,75|Zergling,98,76|Zergling,97,77|Zergling,96,78","dbUpgradesString":"Tier2|NeosteelFrame|LurkerRange|ZergMeleeWeaponsLevel1"},{"Breakpoint":"ALL","Gas":2,"Income":5228,"Army":23444,"Kills":13940,"Upgrades":575,"Tier":0,"Mid":0,"dsUnitsString":"Zergling,68|Baneling,12|Roach,13|Lurker,3|Hydralisk,5","dbUnitsString":"Zergling,90,87|Zergling,91,86|Zergling,92,85|Zergling,93,84|Zergling,94,83|Zergling,95,82|Zergling,96,81|Zergling,89,88|Zergling,88,89|Zergling,87,90|Zergling,86,91|Zergling,85,92|Zergling,84,93|Zergling,97,80|Zergling,98,79|Zergling,99,78|Zergling,100,77|Zergling,101,76|Baneling,78,87|Zergling,94,82|Zergling,95,81|Roach,88,83|Roach,89,82|Roach,90,81|Roach,91,80|Roach,92,79|Roach,87,84|Roach,93,78|Roach,86,85|Roach,85,86|Roach,94,77|Zergling,96,80|Zergling,97,79|Zergling,98,78|Zergling,99,77|Zergling,100,76|Baneling,82,91|Baneling,83,92|Baneling,95,70|Baneling,96,71|Baneling,97,72|Baneling,98,73|Baneling,81,90|Baneling,80,89|Baneling,79,88|Baneling,99,74|Baneling,100,75|Roach,84,87|Roach,83,88|Roach,95,76|Lurker,90,76|Lurker,88,78|Lurker,87,79|Zergling,93,82|Zergling,93,83|Zergling,92,84|Zergling,91,85|Zergling,90,86|Zergling,89,87|Zergling,88,88|Zergling,87,89|Zergling,86,90|Zergling,85,91|Zergling,84,92|Zergling,84,91|Zergling,85,90|Zergling,86,89|Zergling,87,88|Zergling,88,87|Zergling,89,86|Zergling,90,85|Zergling,91,84|Zergling,92,83|Zergling,94,81|Zergling,95,80|Zergling,96,79|Zergling,97,78|Zergling,98,77|Zergling,99,76|Zergling,99,75|Zergling,98,76|Zergling,97,77|Zergling,96,78|Zergling,95,79|Zergling,94,80|Zergling,93,81|Zergling,92,82|Zergling,91,83|Zergling,90,84|Zergling,89,85|Zergling,88,86|Zergling,87,87|Zergling,86,88|Zergling,85,89|Zergling,84,90|Zergling,83,91|Hydralisk,88,81|Hydralisk,89,80|Hydralisk,87,82|Hydralisk,86,83|Hydralisk,85,84","dbUpgradesString":"ZergMissileWeaponsLevel1|ZergGroundArmorsLevel1"}],"POS":5,"REALPOS":5,"NAME":"M\u00E1rkiii","RACE":"Zerg","OPPRACE":"Terran","WIN":false,"TEAM":1,"KILLSUM":13940,"INCOME":5228,"PDURATION":721,"ARMY":23444,"GAS":2},{"Breakpoints":[{"Breakpoint":"MIN5","Gas":0,"Income":1963,"Army":4872,"Kills":3670,"Upgrades":200,"Tier":0,"Mid":0,"dsUnitsString":"Zealot,6|Adept,2|Stalker,7|Immortal,1","dbUnitsString":"Zealot,86,83|Zealot,87,82|Zealot,88,81|Zealot,89,80|Zealot,90,79|Zealot,91,78|Adept,89,79|Adept,87,81|Stalker,87,79|Stalker,89,78|Stalker,86,81|Stalker,91,76|Stalker,84,83|Stalker,93,73|Stalker,81,85|Immortal,84,81","dbUpgradesString":"Charge|Tier2|NeosteelFrame|BlinkTech"},{"Breakpoint":"MIN10","Gas":2,"Income":4272,"Army":17066,"Kills":16965,"Upgrades":350,"Tier":0,"Mid":0,"dsUnitsString":"Zealot,6|Adept,2|Stalker,9|Immortal,4|HighTemplar,4","dbUnitsString":"Zealot,86,83|Zealot,87,82|Zealot,88,81|Zealot,89,80|Zealot,90,79|Zealot,91,78|Adept,89,79|Adept,87,81|Stalker,87,79|Stalker,89,78|Stalker,86,81|Stalker,91,76|Stalker,84,83|Stalker,93,73|Stalker,81,85|Immortal,84,81|Immortal,86,79|Immortal,87,78|Immortal,89,76|Stalker,95,72|Stalker,80,87|HighTemplar,82,84|HighTemplar,92,74|HighTemplar,94,72|HighTemplar,80,86","dbUpgradesString":"PsiStormTech"},{"Breakpoint":"ALL","Gas":2,"Income":5325,"Army":22476,"Kills":20135,"Upgrades":350,"Tier":0,"Mid":0,"dsUnitsString":"Zealot,6|Adept,2|Stalker,9|Immortal,4|HighTemplar,4|VoidRay,3","dbUnitsString":"Zealot,86,83|Zealot,87,82|Zealot,88,81|Zealot,89,80|Zealot,90,79|Zealot,91,78|Adept,89,79|Adept,87,81|Stalker,87,79|Stalker,89,78|Stalker,86,81|Stalker,91,76|Stalker,84,83|Stalker,93,73|Stalker,81,85|Immortal,84,81|Immortal,86,79|Immortal,87,78|Immortal,89,76|Stalker,95,72|Stalker,80,87|HighTemplar,82,84|HighTemplar,92,74|HighTemplar,94,72|HighTemplar,80,86|VoidRay,86,79|VoidRay,87,78|VoidRay,89,76","dbUpgradesString":""}],"POS":6,"REALPOS":6,"NAME":"Harlond","RACE":"Protoss","OPPRACE":"Zerg","WIN":false,"TEAM":1,"KILLSUM":20135,"INCOME":5325,"PDURATION":723,"ARMY":22476,"GAS":2}],"Middle":[{"Gameloop":0,"Team":0},{"Gameloop":876,"Team":2},{"Gameloop":1008,"Team":1},{"Gameloop":1536,"Team":2},{"Gameloop":2244,"Team":1},{"Gameloop":2760,"Team":2},{"Gameloop":2928,"Team":1},{"Gameloop":3300,"Team":2},{"Gameloop":3684,"Team":1},{"Gameloop":3972,"Team":2},{"Gameloop":4116,"Team":1},{"Gameloop":4224,"Team":2},{"Gameloop":4332,"Team":1},{"Gameloop":4788,"Team":2},{"Gameloop":4836,"Team":1},{"Gameloop":7068,"Team":2},{"Gameloop":7212,"Team":1},{"Gameloop":7620,"Team":2},{"Gameloop":7812,"Team":1}],"REPLAY":"724d2e47869031295b8d70121a4769f7a6c4f7630481c74eeca41dc41e59b8f3","GAMETIME":"2021-01-28T21:41:05+01:00","WINNER":0,"DURATION":727,"MINKILLSUM":13940,"MAXKILLSUM":31950,"MINARMY":22476,"MININCOME":5228,"MAXLEAVER":6,"PLAYERCOUNT":6,"REPORTED":0,"ISBRAWL":false,"GAMEMODE":"GameModeStandard","VERSION":"3.0","HASH":"b1d0261219bc16c65ab110a6bc93c55a","REPLAYPATH":"/data/gdsl/replays\\The_Lab_Rats_vs_Kapanyanyi_bogyok.SC2Replay","OBJECTIVE":1,"Upload":"0001-01-01T00:00:00"}