{"DSPlayer":[{"Breakpoints":[{"Breakpoint":"MIN5","Gas":0,"Income":2155,"Army":4095,"Kills":2785,"Upgrades":375,"Tier":0,"Mid":0,"dsUnitsString":"Stalker,16|Zealot,3","dbUnitsString":"Stalker,176,161|Stalker,170,167|Stalker,172,165|Stalker,174,163|Stalker,168,169|Stalker,178,159|Stalker,166,171|Stalker,165,172|Stalker,180,158|Stalker,170,165|Stalker,172,163|Stalker,168,167|Stalker,174,161|Stalker,176,160|Stalker,178,158|Stalker,166,169|Zealot,174,165|Zealot,172,167|Zealot,170,169","dbUpgradesString":"BlinkTech|ProtossGroundArmorsLevel1|ProtossGroundWeaponsLevel1"},{"Breakpoint":"ALL","Gas":0,"Income":3930,"Army":14620,"Kills":10830,"Upgrades":650,"Tier":0,"Mid":0,"dsUnitsString":"Stalker,16|Zealot,7|Observer,1|Disruptor,2|Immortal,2","dbUnitsString":"Stalker,167,156|Stalker,159,162|Stalker,170,148|Stalker,170,150|Stalker,163,158|Stalker,168,152|Stalker,156,163|Stalker,157,162|Stalker,169,150|Stalker,161,160|Stalker,165,158|Stalker,161,158|Stalker,165,154|Stalker,165,156|Stalker,167,154|Stalker,159,160|Zealot,163,154|Zealot,161,156|Zealot,165,152|Observer,165,156|Zealot,157,160|Zealot,155,162|Zealot,171,146|Zealot,167,150|Disruptor,158,163|Disruptor,172,149|Immortal,163,156|Immortal,167,152","dbUpgradesString":"Tier2|NeosteelFrame|Charge|ProtossGroundWeaponsLevel2"}],"POS":1,"REALPOS":1,"NAME":"Kachar","RACE":"Protoss","OPPRACE":"Zerg","WIN":true,"TEAM":0,"KILLSUM":10830,"INCOME":3930,"PDURATION":514,"ARMY":14620,"GAS":0},{"Breakpoints":[{"Breakpoint":"MIN5","Gas":1,"Income":2202,"Army":4750,"Kills":4250,"Upgrades":375,"Tier":0,"Mid":0,"dsUnitsString":"Marine,27|Reaper,2|Marauder,2","dbUnitsString":"Marine,171,146|Marine,168,149|Marine,166,151|Marine,167,150|Marine,159,158|Marine,160,157|Marine,161,156|Marine,162,155|Marine,165,152|Marine,164,153|Marine,163,154|Marine,169,148|Marine,170,147|Marine,158,159|Marine,157,160|Marine,156,161|Marine,155,162|Marine,154,163|Reaper,166,152|Reaper,160,158|Marine,171,147|Marine,155,163|Marauder,159,159|Marauder,167,151|Marine,170,148|Marine,156,162|Marine,169,149|Marine,157,161|Marine,168,150|Marine,158,160|Marine,161,157","dbUpgradesString":"ShieldWall|Stimpack|TerranInfantryWeaponsLevel1|PunisherGrenades|TerranInfantryArmorsLevel1"},{"Breakpoint":"ALL","Gas":2,"Income":4243,"Army":15150,"Kills":10145,"Upgrades":625,"Tier":0,"Mid":0,"dsUnitsString":"Marine,53|Reaper,2|Marauder,6","dbUnitsString":"Marine,171,146|Marine,168,149|Marine,166,151|Marine,167,150|Marine,159,158|Marine,160,157|Marine,161,156|Marine,162,155|Marine,165,152|Marine,164,153|Marine,163,154|Marine,169,148|Marine,170,147|Marine,158,159|Marine,157,160|Marine,156,161|Marine,155,162|Marine,154,163|Reaper,166,152|Reaper,160,158|Marine,171,147|Marine,155,163|Marauder,159,159|Marauder,167,151|Marine,170,148|Marine,156,162|Marine,169,149|Marine,157,161|Marine,168,150|Marine,158,160|Marine,161,157|Marine,165,153|Marine,164,154|Marine,163,155|Marine,162,156|Marine,172,147|Marine,155,164|Marine,157,162|Marine,170,149|Marine,168,151|Marine,159,160|Marine,161,158|Marine,166,153|Marine,164,155|Marine,163,156|Marine,171,148|Marine,156,163|Marine,158,161|Marine,169,150|Marine,167,152|Marine,160,159|Marine,162,157|Marine,165,154|Marine,171,149|Marine,157,163|Marauder,156,164|Marauder,172,148|Marauder,170,150|Marauder,158,162|Marine,169,151|Marine,159,161","dbUpgradesString":"Tier2|NeosteelFrame|TerranInfantryWeaponsLevel2|TerranInfantryArmorsLevel2"}],"POS":2,"REALPOS":2,"NAME":"Tris","RACE":"Terran","OPPRACE":"Protoss","WIN":true,"TEAM":0,"KILLSUM":10145,"INCOME":4243,"PDURATION":514,"ARMY":15150,"GAS":2},{"Breakpoints":[{"Breakpoint":"MIN5","Gas":0,"Income":2155,"Army":4510,"Kills":3515,"Upgrades":300,"Tier":0,"Mid":0,"dsUnitsString":"Roach,5|Hydralisk,8|Infestor,2|Lurker,1","dbUnitsString":"Roach,159,168|Roach,161,168|Hydralisk,160,169|Hydralisk,161,169|Hydralisk,162,169|Roach,164,168|Hydralisk,163,169|Hydralisk,164,169|Roach,165,168|Hydralisk,165,169|Infestor,165,170|Infestor,163,170|Lurker,163,167|Hydralisk,166,169|Hydralisk,167,169|Roach,167,168","dbUpgradesString":"Tier2|NeosteelFrame|EvolveGroovedSpines|ZergGroundArmorsLevel1|ZergMissileWeaponsLevel1"},{"Breakpoint":"ALL","Gas":1,"Income":4024,"Army":12480,"Kills":14055,"Upgrades":400,"Tier":0,"Mid":0,"dsUnitsString":"Roach,5|Hydralisk,7|Lurker,4|Infestor,2|Overseer,1|Queen,2","dbUnitsString":"Roach,154,163|Roach,158,159|Hydralisk,156,165|Hydralisk,158,163|Hydralisk,160,161|Roach,162,155|Hydralisk,162,159|Lurker,160,160|Roach,166,151|Hydralisk,169,152|Infestor,168,154|Infestor,162,160|Lurker,156,163|Hydralisk,171,150|Hydralisk,173,148|Roach,171,146|Lurker,171,148|Overseer,164,156|Queen,170,150|Queen,158,162|Lurker,168,152","dbUpgradesString":"LurkerRange"}],"POS":3,"REALPOS":3,"NAME":"imsux","RACE":"Zerg","OPPRACE":"Terran","WIN":true,"TEAM":0,"KILLSUM":14055,"INCOME":4024,"PDURATION":514,"ARMY":12480,"GAS":1},{"Breakpoints":[{"Breakpoint":"MIN5","Gas":0,"Income":1990,"Army":3870,"Kills":2450,"Upgrades":225,"Tier":0,"Mid":0,"dsUnitsString":"Zergling,72|Infestor,3","dbUnitsString":"Zergling,101,76|Zergling,100,77|Zergling,99,78|Zergling,98,79|Zergling,97,80|Zergling,96,81|Zergling,95,82|Zergling,94,83|Zergling,93,84|Zergling,92,85|Zergling,91,86|Zergling,90,87|Zergling,89,88|Zergling,88,89|Zergling,87,90|Zergling,86,91|Zergling,85,92|Zergling,84,93|Zergling,84,92|Zergling,100,76|Zergling,99,77|Zergling,98,78|Zergling,97,79|Zergling,96,80|Zergling,85,91|Zergling,86,90|Zergling,87,89|Zergling,88,88|Zergling,89,87|Zergling,90,86|Zergling,91,85|Zergling,92,84|Zergling,93,83|Zergling,94,82|Zergling,95,81|Zergling,100,75|Zergling,99,76|Zergling,98,77|Zergling,97,78|Zergling,96,78|Zergling,96,79|Zergling,95,80|Zergling,94,81|Zergling,90,85|Zergling,92,83|Zergling,93,82|Zergling,91,84|Zergling,89,86|Zergling,87,88|Zergling,88,87|Zergling,86,89|Zergling,85,90|Zergling,83,92|Zergling,84,91|Zergling,97,77|Zergling,98,76|Zergling,99,75|Zergling,95,79|Zergling,94,80|Zergling,93,81|Zergling,92,82|Zergling,91,83|Zergling,90,84|Zergling,89,85|Zergling,88,86|Zergling,87,87|Zergling,86,88|Zergling,85,89|Zergling,84,90|Zergling,83,91|Zergling,99,74|Zergling,98,75|Infestor,86,85|Infestor,92,79|Infestor,89,82","dbUpgradesString":"zerglingmovementspeed|ZergMeleeWeaponsLevel1|Tier2|NeosteelFrame"},{"Breakpoint":"ALL","Gas":0,"Income":3602,"Army":11065,"Kills":7980,"Upgrades":325,"Tier":0,"Mid":0,"dsUnitsString":"Zergling,72|Infestor,1|Lurker,4|Queen,1","dbUnitsString":"Zergling,101,76|Zergling,100,77|Zergling,99,78|Zergling,98,79|Zergling,97,80|Zergling,96,81|Zergling,95,82|Zergling,94,83|Zergling,93,84|Zergling,92,85|Zergling,91,86|Zergling,90,87|Zergling,89,88|Zergling,88,89|Zergling,87,90|Zergling,86,91|Zergling,85,92|Zergling,84,93|Zergling,84,92|Zergling,100,76|Zergling,99,77|Zergling,98,78|Zergling,97,79|Zergling,96,80|Zergling,85,91|Zergling,86,90|Zergling,87,89|Zergling,88,88|Zergling,89,87|Zergling,90,86|Zergling,91,85|Zergling,92,84|Zergling,93,83|Zergling,94,82|Zergling,95,81|Zergling,100,75|Zergling,99,76|Zergling,98,77|Zergling,97,78|Zergling,96,78|Zergling,96,79|Zergling,95,80|Zergling,94,81|Zergling,90,85|Zergling,92,83|Zergling,93,82|Zergling,91,84|Zergling,89,86|Zergling,87,88|Zergling,88,87|Zergling,86,89|Zergling,85,90|Zergling,83,92|Zergling,84,91|Zergling,97,77|Zergling,98,76|Zergling,99,75|Zergling,95,79|Zergling,94,80|Zergling,93,81|Zergling,92,82|Zergling,91,83|Zergling,90,84|Zergling,89,85|Zergling,88,86|Zergling,87,87|Zergling,86,88|Zergling,85,89|Zergling,84,90|Zergling,83,91|Zergling,99,74|Zergling,98,75|Infestor,89,82|Lurker,95,76|Lurker,84,88|Lurker,92,79|Lurker,87,85|Queen,89,79","dbUpgradesString":"LurkerRange"}],"POS":4,"REALPOS":4,"NAME":"IIIIIIIIIIII","RACE":"Zerg","OPPRACE":"Protoss","WIN":false,"TEAM":1,"KILLSUM":7980,"INCOME":3602,"PDURATION":514,"ARMY":11065,"GAS":0},{"Breakpoints":[{"Breakpoint":"MIN5","Gas":0,"Income":1990,"Army":4105,"Kills":2070,"Upgrades":275,"Tier":0,"Mid":0,"dsUnitsString":"Stalker,9|Sentry,2|DarkTemplar,2","dbUnitsString":"Stalker,89,86|Stalker,91,84|Stalker,93,82|Stalker,95,80|Stalker,99,77|Stalker,87,88|Stalker,97,78|Stalker,85,90|Sentry,95,82|Stalker,84,91|DarkTemplar,101,76|DarkTemplar,84,93|Sentry,89,88","dbUpgradesString":"BlinkTech|ProtossGroundWeaponsLevel1|Tier2|NeosteelFrame"},{"Breakpoint":"ALL","Gas":1,"Income":3675,"Army":9022,"Kills":3920,"Upgrades":425,"Tier":0,"Mid":0,"dsUnitsString":"Stalker,9|Sentry,2|DarkTemplar,2|HighTemplar,2","dbUnitsString":"Stalker,89,86|Stalker,91,84|Stalker,93,82|Stalker,95,80|Stalker,99,77|Stalker,87,88|Stalker,97,78|Stalker,85,90|Sentry,94,81|Stalker,84,91|DarkTemplar,101,76|DarkTemplar,84,93|Sentry,88,87|HighTemplar,93,81|HighTemplar,87,87","dbUpgradesString":"PsiStormTech|Tier3"}],"POS":5,"REALPOS":5,"NAME":"ALLin","RACE":"Protoss","OPPRACE":"Terran","WIN":false,"TEAM":1,"KILLSUM":3920,"INCOME":3675,"PDURATION":514,"ARMY":9022,"GAS":1},{"Breakpoints":[{"Breakpoint":"MIN5","Gas":0,"Income":1990,"Army":4240,"Kills":5660,"Upgrades":300,"Tier":0,"Mid":0,"dsUnitsString":"Marine,18|Marauder,6","dbUnitsString":"Marine,80,89|Marine,81,88|Marine,82,87|Marine,83,86|Marine,84,85|Marine,85,84|Marauder,83,90|Marauder,89,84|Marine,86,83|Marine,87,82|Marine,88,81|Marine,89,80|Marauder,92,81|Marine,90,79|Marine,92,77|Marine,91,78|Marine,93,76|Marine,94,75|Marauder,95,78|Marauder,86,87|Marine,95,74|Marine,96,73|Marine,97,72|Marauder,98,75","dbUpgradesString":"Stimpack|TerranInfantryWeaponsLevel1|TerranInfantryArmorsLevel1|Tier2|NeosteelFrame"},{"Breakpoint":"ALL","Gas":1,"Income":3669,"Army":8349,"Kills":9155,"Upgrades":575,"Tier":0,"Mid":0,"dsUnitsString":"Marine,30|Marauder,8|HellionTank,5","dbUnitsString":"Marine,80,89|Marine,81,88|Marine,82,87|Marine,83,86|Marine,84,85|Marine,85,84|Marauder,83,89|Marauder,91,81|Marine,86,83|Marine,87,82|Marine,88,81|Marine,89,80|Marauder,93,79|Marine,90,79|Marine,92,77|Marine,91,78|Marine,93,76|Marine,94,75|Marauder,95,77|Marauder,89,83|Marine,95,74|Marine,96,73|Marine,97,72|Marauder,97,75|HellionTank,98,75|HellionTank,94,79|HellionTank,90,82|Marauder,87,85|HellionTank,87,86|Marauder,85,87|HellionTank,83,90|Marine,78,87|Marine,79,86|Marine,80,85|Marine,81,84|Marine,82,83|Marine,83,82|Marine,90,75|Marine,91,74|Marine,92,73|Marine,93,72|Marine,94,71|Marine,95,70","dbUpgradesString":"TerranInfantryWeaponsLevel2|HighCapacityBarrels|PunisherGrenades|ShieldWall"}],"POS":6,"REALPOS":6,"NAME":"Necroshader","RACE":"Terran","OPPRACE":"Zerg","WIN":false,"TEAM":1,"KILLSUM":9155,"INCOME":3669,"PDURATION":514,"ARMY":8349,"GAS":1}],"Middle":[{"Gameloop":0,"Team":0},{"Gameloop":840,"Team":2},{"Gameloop":1212,"Team":1},{"Gameloop":1812,"Team":2},{"Gameloop":2820,"Team":1},{"Gameloop":3720,"Team":2},{"Gameloop":4332,"Team":1},{"Gameloop":5220,"Team":2},{"Gameloop":5616,"Team":1}],"REPLAY":"724d2e47869031295b8d70121a4769f7b5599354ed25f665b03b96a91b2023e6","GAMETIME":"2021-01-28T22:15:41+01:00","WINNER":0,"DURATION":516,"MINKILLSUM":3920,"MAXKILLSUM":14055,"MINARMY":8349,"MININCOME":3602,"MAXLEAVER":2,"PLAYERCOUNT":6,"REPORTED":0,"ISBRAWL":false,"GAMEMODE":"GameModeStandard","VERSION":"3.0","HASH":"4cfc3d6d3732c168c0e88f82193e34b6","REPLAYPATH":"/data/gdsl/replays\\GrumpyKittens_vs_strikE_PTZvsZPT_GS.SC2Replay","OBJECTIVE":1,"Upload":"0001-01-01T00:00:00"}